latent_space_visualizer/__init__.py
latent_space_visualizer-0.0.3.dist-info/METADATA
latent_space_visualizer-0.0.3.dist-info/WHEEL
latent_space_visualizer-0.0.3.dist-info/top_level.txt
latent_space_visualizer-0.0.3.dist-info/RECORD
