Metadata-Version: 2.1
Name: latent-space-visualizer
Version: 0.0.3
Summary: A tool for visualizing latent spaces.
Home-page: https://github.com/compSPI/LatentSpaceVisualizer
Author: Deeban Ramalingam
Author-email: rdeeban@gmail.com
License: UNKNOWN
Platform: UNKNOWN
Classifier: Programming Language :: Python :: 3
Classifier: License :: OSI Approved :: MIT License
Classifier: Operating System :: OS Independent
Requires-Python: >=3.7
Requires-Dist: bokeh
Requires-Dist: jupyterlab
Requires-Dist: scikit-learn
Requires-Dist: h5py
Requires-Dist: numpy
Requires-Dist: kora
Requires-Dist: setuptools
